{"videos":[{"_id":"65b00d276975f7001820a025","isFree":false,"status":"COMPLETED","date":"2024-01-24T00:00:00.000Z","startTime":"2024-01-24T12:45:41.000Z","isDPPNotes":false,"dRoomId":"6433b5617f779e5090d128b0","isBatchDoubtEnabled":true,"isChatEnabled":false,"isCommentDisabled":false,"isDPPVideos":false,"isDoubtEnabled":true,"isPathshala":false,"restrictedSchedule":false,"endTime":"2024-01-24T13:43:50.000Z","restrictedTime":0,"tags":[{"_id":"65b00c9e860f704cf858a1e4","name":"Doubts and Motivational\u00a0Session"}],"teachers":["60ae176806a18c00129ca96c"],"timeline":[],"topic":"Doubts and Motivational Session : Interactive Session || Video Only","url":"https:\/\/d1d34p8vz63oiq.cloudfront.net\/358e4d33-f5b0-47ac-9f66-673f1302814c\/master.mpd","urlType":"penpencilvdo","ytStreamKey":null,"ytStreamUrl":null,"lectureType":"LIVE","whiteboardType":null,"videoDetails":{"_id":"65b118328b5be60018fff277","id":"65b118328b5be60018fff277","name":"Doubts and Motivational Session : Interactive Session","image":"https:\/\/static.pw.live\/5eb393ee95fab7468a79d189\/177a8177-1980-4958-994e-cd607c5dd1c7.png","videoUrl":"https:\/\/d1d34p8vz63oiq.cloudfront.net\/358e4d33-f5b0-47ac-9f66-673f1302814c\/master.mpd","description":"<!DOCTYPE html>\n<html>\n<head>\n<\/head>\n<body>\n\n<\/body>\n<\/html>","duration":"00:57:20","status":"Ready","types":["DASH","HLS"],"createdAt":"2024-01-24T14:01:22.747Z","drmProtected":false,"findKey":"65b00d276975f7001820a025"},"conversationId":"65b00d276975f7001820a027","roomId":null,"isLocked":false}],"notes":[],"DppNotes":[],"DppVideos":[],"exercises":[]}