{"videos":[],"notes":[{"_id":"664c657d3801c00018944a54","isFree":false,"status":"PENDING","date":"2024-05-21T00:00:00.000Z","startTime":"2024-05-21T04:30:50.000Z","isDPPNotes":false,"homeworkIds":[{"_id":"664c5f2c42e4d3b1716ad68c","actions":["Open","Download","Print"],"topic":"SST : PYQs","note":"PYQ","attachmentIds":[{"_id":"664c5f2593eb8c00181951b8","baseUrl":"https:\/\/d2bps9p1kiy4ka.cloudfront.net\/","key":"5eb393ee95fab7468a79d189\/a11db471-52a7-4ca5-ac24-ff6a9fbfaf98.pdf","name":"SST  PYQs.pdf"}],"batchSubjectId":"664c4a623700a6001855a87b","solutionVideoId":null,"solutionVideoType":"none","solutionVideoUrl":null}],"dRoomId":"664c48940a8ec3f4b8e9ccdf","isBatchDoubtEnabled":true}],"DppNotes":[],"DppVideos":[],"exercises":[]}