{"videos":[{"_id":"671fbced6eef20f38c9e3e9a","isFree":false,"status":"PENDING","date":"2024-10-29T00:00:00.000Z","startTime":"2024-10-29T09:30:00.000Z","isDPPNotes":false,"dRoomId":"664c48940a8ec3f4b8e9ccdf","isBatchDoubtEnabled":true,"isChatEnabled":false,"isCommentDisabled":false,"isDPPVideos":false,"isDoubtEnabled":true,"isPathshala":false,"restrictedSchedule":false,"endTime":"2024-10-29T09:30:00.000Z","restrictedTime":0,"tags":[{"_id":"66f62205a4d3b86de1b4ed67","name":"Metals and Non Metal"}],"teachers":["624bf1e629ac560011dbe15d"],"timeline":[],"topic":"Metals and Non Metals 06 : NCERT Question Practice || No DHA || Recorded","url":"https:\/\/d1d34p8vz63oiq.cloudfront.net\/1d2ef492-ff12-4ad1-a27e-73a0a1f4a6ad\/master.mpd","urlType":"penpencilvdo","ytStreamKey":null,"ytStreamUrl":null,"lectureType":"RECORDED","whiteboardType":"NOTE3","videoDetails":{"_id":"671fc15c5538bdf96295a69e","id":"671fc15c5538bdf96295a69e","name":"Metals and Non Metals 06 : NCERT Question Practice || Recorded","image":"https:\/\/static.pw.live\/5eb393ee95fab7468a79d189\/ADMIN\/e6d7c367-5f62-4b2d-9496-69282ae52f54.png","videoUrl":"https:\/\/d1d34p8vz63oiq.cloudfront.net\/1d2ef492-ff12-4ad1-a27e-73a0a1f4a6ad\/master.mpd","description":"<!DOCTYPE html>\n<html>\n<head>\n<\/head>\n<body>\n\n<\/body>\n<\/html>","duration":"01:13:31","status":"Ready","types":["DASH","HLS"],"createdAt":"2024-10-28T16:52:44.725Z","drmProtected":false,"findKey":"671fbced6eef20f38c9e3e9a"},"conversationId":null,"roomId":null,"isLocked":false},{"_id":"671714c84f4facd859a79ba8","isFree":false,"status":"COMPLETED","date":"2024-10-22T00:00:00.000Z","startTime":"2024-10-22T09:30:00.000Z","isDPPNotes":false,"dRoomId":"664c48940a8ec3f4b8e9ccdf","isBatchDoubtEnabled":true,"isChatEnabled":false,"isCommentDisabled":false,"isDPPVideos":false,"isDoubtEnabled":true,"isPathshala":false,"restrictedSchedule":false,"endTime":"2024-10-22T10:48:00.000Z","restrictedTime":0,"tags":[{"_id":"66f62205a4d3b86de1b4ed67","name":"Metals and Non Metal"}],"teachers":["624bf1e629ac560011dbe15d"],"timeline":[],"topic":"Metals and Non Metals 05 : Occurrence of Metals (Part - 02)","url":"https:\/\/d1d34p8vz63oiq.cloudfront.net\/db4ae1b6-f894-44bd-95bb-4879824c409a\/master.mpd","urlType":"penpencilvdo","ytStreamKey":null,"ytStreamUrl":null,"lectureType":"LIVE","whiteboardType":"NOTE3","videoDetails":{"_id":"671783e27d27d6e9af6c0a09","id":"671783e27d27d6e9af6c0a09","name":"Metals and Non Metals 05 : Occurrence of Metals (Part - 02)","image":"https:\/\/static.pw.live\/5eb393ee95fab7468a79d189\/ADMIN\/6b45c212-10ac-449b-9435-4e679d2fe081.png","videoUrl":"https:\/\/d1d34p8vz63oiq.cloudfront.net\/db4ae1b6-f894-44bd-95bb-4879824c409a\/master.mpd","description":"<!DOCTYPE html>\n<html>\n<head>\n<\/head>\n<body>\n<p>live to vod<\/p>\n<\/body>\n<\/html>","duration":"01:18:24","status":"Ready","types":["DASH","HLS"],"createdAt":"2024-10-22T10:52:18.827Z","drmProtected":false,"findKey":"671714c84f4facd859a79ba8"},"conversationId":"671714c87e2c237d65386ee4","roomId":null,"isLocked":false},{"_id":"6711bc06dddc2cd517db4363","isFree":false,"status":"PENDING","date":"2024-10-18T00:00:00.000Z","startTime":"2024-10-18T11:00:00.000Z","isDPPNotes":false,"dRoomId":"664c48940a8ec3f4b8e9ccdf","isBatchDoubtEnabled":true,"isChatEnabled":false,"isCommentDisabled":false,"isDPPVideos":false,"isDoubtEnabled":true,"isPathshala":false,"restrictedSchedule":false,"endTime":"2024-10-18T11:00:00.000Z","restrictedTime":0,"tags":[{"_id":"66f62205a4d3b86de1b4ed67","name":"Metals and Non Metal"}],"teachers":["624bf1e629ac560011dbe15d"],"timeline":[],"topic":"Metals and Non Metals 04 : Occurrence of Metals (Part - 01) || Recorded","url":"https:\/\/d1d34p8vz63oiq.cloudfront.net\/c8d16511-b5b9-4f2b-ac09-e7ed19690e9f\/master.mpd","urlType":"penpencilvdo","ytStreamKey":null,"ytStreamUrl":null,"lectureType":"RECORDED","whiteboardType":"NOTE3","videoDetails":{"_id":"6711fd673b365b023db056c5","id":"6711fd673b365b023db056c5","name":"Metals and Non Metals 04 : Occurrence of Metals (Part - 01)","image":"https:\/\/static.pw.live\/5eb393ee95fab7468a79d189\/ADMIN\/7f566e95-f89a-4e3b-b302-ea112b6afed1.png","videoUrl":"https:\/\/d1d34p8vz63oiq.cloudfront.net\/c8d16511-b5b9-4f2b-ac09-e7ed19690e9f\/master.mpd","description":"<!DOCTYPE html>\n<html>\n<head>\n<\/head>\n<body>\n\n<\/body>\n<\/html>","duration":"01:00:49","status":"Ready","types":["DASH","HLS"],"createdAt":"2024-10-18T06:17:11.783Z","drmProtected":false,"findKey":"6711bc06dddc2cd517db4363"},"conversationId":"6711bc069c7dc187c7f0d4bb","roomId":null,"isLocked":false},{"_id":"670802f619347323c1c4d4ae","isFree":false,"status":"PENDING","date":"2024-10-11T00:00:00.000Z","startTime":"2024-10-11T11:00:00.000Z","isDPPNotes":false,"dRoomId":"664c48940a8ec3f4b8e9ccdf","isBatchDoubtEnabled":true,"isChatEnabled":false,"isCommentDisabled":false,"isDPPVideos":false,"isDoubtEnabled":true,"isPathshala":false,"restrictedSchedule":false,"endTime":"2024-10-11T11:00:00.000Z","restrictedTime":0,"tags":[{"_id":"66f62205a4d3b86de1b4ed67","name":"Metals and Non Metal"}],"teachers":["624bf1e629ac560011dbe15d"],"timeline":[],"topic":"Metals and Non Metals 03 : How do Metals and Non-Metals React? || Recorded","url":"https:\/\/d1d34p8vz63oiq.cloudfront.net\/60ddbc59-4f92-446e-91f1-fd158b3d7b17\/master.mpd","urlType":"penpencilvdo","ytStreamKey":null,"ytStreamUrl":null,"lectureType":"RECORDED","whiteboardType":"NOTE3","videoDetails":{"_id":"6703f3149ff979a1a3132276","id":"6703f3149ff979a1a3132276","name":"Metals And Non-Metals Lec-03 (Sanya Mam) Udaan 2.0","image":"https:\/\/static.pw.live\/5eb393ee95fab7468a79d189\/ADMIN\/9fb006bf-9d05-461b-a453-517270fcf060.png","videoUrl":"https:\/\/d1d34p8vz63oiq.cloudfront.net\/60ddbc59-4f92-446e-91f1-fd158b3d7b17\/master.mpd","description":"<!DOCTYPE html>\n<html>\n<head>\n<\/head>\n<body>\n\n<\/body>\n<\/html>","duration":"01:11:01","status":"Ready","types":["DASH","HLS"],"createdAt":"2024-10-07T14:41:24.048Z","drmProtected":false,"findKey":"670802f619347323c1c4d4ae"},"conversationId":"670802f69c6704c95c054210","roomId":null,"isLocked":false},{"_id":"66ff685e5b935d0595d5d5ff","isFree":false,"status":"COMPLETED","date":"2024-10-04T00:00:00.000Z","startTime":"2024-10-04T11:15:00.000Z","isDPPNotes":false,"dRoomId":"664c48940a8ec3f4b8e9ccdf","isBatchDoubtEnabled":true,"isChatEnabled":false,"isCommentDisabled":false,"isDPPVideos":false,"isDoubtEnabled":true,"isPathshala":false,"restrictedSchedule":false,"endTime":"2024-10-04T12:40:02.907Z","restrictedTime":0,"tags":[{"_id":"66f62205a4d3b86de1b4ed67","name":"Metals and Non Metal"}],"teachers":["624bf1e629ac560011dbe15d"],"timeline":[],"topic":"Metals and Non Metals 02 : Chemical Properties of Metals (Continued) || Chemical Properties of Non-Metals || Rescheduled @04:45 PM","url":"https:\/\/d1d34p8vz63oiq.cloudfront.net\/d5d506de-d8ce-48e9-ac6b-ff2c3f543a8b\/master.mpd","urlType":"penpencilvdo","ytStreamKey":null,"ytStreamUrl":null,"lectureType":"LIVE","whiteboardType":"NOTE3","videoDetails":{"_id":"66ffed4cb4ae2148a5e3d7f7","id":"66ffed4cb4ae2148a5e3d7f7","name":"Metals and Non Metals 02 : Chemical Properties of Metals (Continued) || Chemical Properties of Non-Metals || Rescheduled @04:45 PM","image":"https:\/\/static.pw.live\/5eb393ee95fab7468a79d189\/ADMIN\/8b8a6530-f9f8-438b-830b-4c7c1a553364.png","videoUrl":"https:\/\/d1d34p8vz63oiq.cloudfront.net\/d5d506de-d8ce-48e9-ac6b-ff2c3f543a8b\/master.mpd","description":"<!DOCTYPE html>\n<html>\n<head>\n<\/head>\n<body>\n<p>live to vod<\/p>\n<\/body>\n<\/html>","duration":"01:23:44","status":"Ready","types":["DASH","HLS"],"createdAt":"2024-10-04T13:27:40.448Z","drmProtected":false,"findKey":"66ff685e5b935d0595d5d5ff"},"conversationId":"66ff685e2c695783c514ce41","roomId":null,"isLocked":false},{"_id":"66f6226e3697a2b7c0b4444a","isFree":false,"status":"COMPLETED","date":"2024-09-27T00:00:00.000Z","startTime":"2024-09-27T11:00:00.000Z","isDPPNotes":false,"dRoomId":"664c48940a8ec3f4b8e9ccdf","isBatchDoubtEnabled":true,"isChatEnabled":false,"isCommentDisabled":false,"isDPPVideos":false,"isDoubtEnabled":true,"isPathshala":false,"restrictedSchedule":false,"endTime":"2024-09-27T12:23:22.034Z","restrictedTime":0,"tags":[{"_id":"66f62205a4d3b86de1b4ed67","name":"Metals and Non Metal"}],"teachers":["624bf1e629ac560011dbe15d"],"timeline":[],"topic":"Metals and Non Metals 01 : Physical Properties of Metals and Non-metals || Chemical Properties of Metals","url":"https:\/\/d1d34p8vz63oiq.cloudfront.net\/c6229633-3c79-4034-b4ab-48d2bf561a85\/master.mpd","urlType":"penpencilvdo","ytStreamKey":null,"ytStreamUrl":null,"lectureType":"LIVE","whiteboardType":"NOTE3","videoDetails":{"_id":"66f6b0cf49b8e01256190e3b","id":"66f6b0cf49b8e01256190e3b","name":"Metals and Non Metals 01 : Physical Properties of Metals and Non-metals and Their Exceptions || Chemical Properties of Metals","image":"https:\/\/static.pw.live\/5eb393ee95fab7468a79d189\/ADMIN\/913ce2ef-66eb-4754-b308-5f311c56963a.png","videoUrl":"https:\/\/d1d34p8vz63oiq.cloudfront.net\/c6229633-3c79-4034-b4ab-48d2bf561a85\/master.mpd","description":"<!DOCTYPE html>\n<html>\n<head>\n<\/head>\n<body>\n<p>live to vod<\/p>\n<\/body>\n<\/html>","duration":"01:21:52","status":"Ready","types":["DASH","HLS"],"createdAt":"2024-09-27T13:19:11.671Z","drmProtected":false,"findKey":"66f6226e3697a2b7c0b4444a"},"conversationId":"66f6226e95f617a9429c51aa","roomId":null,"isLocked":false}],"notes":[{"_id":"671fbced6eef20f38c9e3e9a","isFree":false,"status":"PENDING","date":"2024-10-29T00:00:00.000Z","startTime":"2024-10-29T09:30:00.000Z","isDPPNotes":false,"homeworkIds":[{"_id":"6720a129c879b91ecf6b389a","actions":["Open","Download","Print"],"topic":"Metals and Non Metals 06 : Class Notes || Udaan 2.0 2025","note":"Class Notes","attachmentIds":[{"_id":"6720a124dbea0b2099271e90","baseUrl":"https:\/\/static.pw.live\/","key":"5eb393ee95fab7468a79d189\/ADMIN\/0284de2c-867f-40bd-ad07-6cd0327b2005.pdf","name":"Metals and Non Metals 06_Class Notes.pdf"}],"batchSubjectId":"664c48d84985820018a8c4e9","solutionVideoId":null,"solutionVideoType":"none","solutionVideoUrl":null}],"dRoomId":"664c48940a8ec3f4b8e9ccdf","isBatchDoubtEnabled":true},{"_id":"671714c84f4facd859a79ba8","isFree":false,"status":"COMPLETED","date":"2024-10-22T00:00:00.000Z","startTime":"2024-10-22T09:30:00.000Z","isDPPNotes":false,"homeworkIds":[{"_id":"6717857c4f4facd859ae5313","actions":["Open","Download","Print"],"topic":"Metals and Non Metals 05 : Class Notes || Udaan 2.0 2025","note":"Class Notes","attachmentIds":[{"_id":"67178576f7d0584368828dd9","baseUrl":"https:\/\/static.pw.live\/","key":"5eb393ee95fab7468a79d189\/ADMIN\/287bf4a9-c2f3-4c25-af81-4f24172e7951.pdf","name":"Metals and Non Metals 05_Class Notes.pdf"}],"batchSubjectId":"664c48d84985820018a8c4e9","solutionVideoId":null,"solutionVideoType":"none","solutionVideoUrl":null}],"dRoomId":"664c48940a8ec3f4b8e9ccdf","isBatchDoubtEnabled":true},{"_id":"6711bc06dddc2cd517db4363","isFree":false,"status":"PENDING","date":"2024-10-18T00:00:00.000Z","startTime":"2024-10-18T11:00:00.000Z","isDPPNotes":false,"homeworkIds":[{"_id":"671211b2111b301c4ed31ddd","actions":["Open","Download","Print"],"topic":"Metals and Non Metals 04 : Class Notes || Udaan 2.0 2025","note":"Class Notes","attachmentIds":[{"_id":"671211afae104e65d25a7c6b","baseUrl":"https:\/\/static.pw.live\/","key":"5eb393ee95fab7468a79d189\/ADMIN\/3209fba6-4f2a-4c2a-a329-e6ae32f519d7.pdf","name":"Metals and Non Metals 04 _Class Notes.pdf"}],"batchSubjectId":"664c48d84985820018a8c4e9","solutionVideoId":null,"solutionVideoType":"none","solutionVideoUrl":null}],"dRoomId":"664c48940a8ec3f4b8e9ccdf","isBatchDoubtEnabled":true},{"_id":"670802f619347323c1c4d4ae","isFree":false,"status":"PENDING","date":"2024-10-11T00:00:00.000Z","startTime":"2024-10-11T11:00:00.000Z","isDPPNotes":false,"homeworkIds":[{"_id":"6708effbc2a9cf56b354b0ec","actions":["Open","Download","Print"],"topic":"Metals and Non Metals 03 : Class Notes || Udaan 2.0 2025","note":"Class Notes","attachmentIds":[{"_id":"6708efe2e17871f16b537deb","baseUrl":"https:\/\/static.pw.live\/","key":"5eb393ee95fab7468a79d189\/ADMIN\/eb5d3085-ca34-4588-9fff-3962265a835c.pdf","name":"Metals and Non Metals 03_Class Notes.pdf"}],"batchSubjectId":"664c48d84985820018a8c4e9","solutionVideoId":null,"solutionVideoType":"none","solutionVideoUrl":null}],"dRoomId":"664c48940a8ec3f4b8e9ccdf","isBatchDoubtEnabled":true},{"_id":"66ff685e5b935d0595d5d5ff","isFree":false,"status":"COMPLETED","date":"2024-10-04T00:00:00.000Z","startTime":"2024-10-04T11:15:00.000Z","isDPPNotes":false,"homeworkIds":[{"_id":"66ffe4a909fa833bfdc3b71c","actions":["Open","Download","Print"],"topic":"Metals and Non Metals 02 : Class Notes || Udaan 2.0 2025","note":"Class Notes","attachmentIds":[{"_id":"66ffe4a5ffea4d8db0d5e31f","baseUrl":"https:\/\/static.pw.live\/","key":"5eb393ee95fab7468a79d189\/ADMIN\/77fd1d70-f9e8-470a-a640-b28077ea00e6.pdf","name":"Metals and Non-Metals_02_Class Notes.pdf"}],"batchSubjectId":"664c48d84985820018a8c4e9","solutionVideoId":null,"solutionVideoType":"none","solutionVideoUrl":null}],"dRoomId":"664c48940a8ec3f4b8e9ccdf","isBatchDoubtEnabled":true},{"_id":"66f6226e3697a2b7c0b4444a","isFree":false,"status":"COMPLETED","date":"2024-09-27T00:00:00.000Z","startTime":"2024-09-27T11:00:00.000Z","isDPPNotes":false,"homeworkIds":[{"_id":"66f6a49e1a3069d22a0e3d7e","actions":["Open","Download","Print"],"topic":"Metals and Non Metals 01 : Class Notes || Udaan 2.0 2025","note":"Class Notes","attachmentIds":[{"_id":"66f6a9156a3c56c9b30466c7","baseUrl":"https:\/\/static.pw.live\/","key":"5eb393ee95fab7468a79d189\/ADMIN\/a0659528-3611-4306-bb7f-375681848f50.pdf","name":"Metals and Non-Metals 01 _Class Notes.pdf"}],"batchSubjectId":"664c48d84985820018a8c4e9","solutionVideoId":null,"solutionVideoType":"none","solutionVideoUrl":null}],"dRoomId":"664c48940a8ec3f4b8e9ccdf","isBatchDoubtEnabled":true}],"DppNotes":[{"_id":"67175970318d8c8a3a262340","isFree":false,"status":"PENDING","date":"2024-10-22T00:00:00.000Z","startTime":"2024-10-22T09:30:00.000Z","isDPPNotes":true,"homeworkIds":[{"_id":"67175935d509922e33bed4db","actions":["Open","Download","Print"],"topic":"Metals and Non Metals : DHA 05 || Udaan 2.0 2025","note":"DPP","attachmentIds":[{"_id":"671759309ca4efee561cead7","baseUrl":"https:\/\/static.pw.live\/","key":"5eb393ee95fab7468a79d189\/ADMIN\/91d62160-5827-4dee-9c41-347e1737dcee.pdf","name":"Metals and Non Metals_DHA 05.pdf"}],"batchSubjectId":"664c48d84985820018a8c4e9","solutionVideoId":null,"solutionVideoType":"none","solutionVideoUrl":null}],"dRoomId":"664c48940a8ec3f4b8e9ccdf","isBatchDoubtEnabled":true},{"_id":"67123b27ac007d7247153fbb","isFree":false,"status":"PENDING","date":"2024-10-18T00:00:00.000Z","startTime":"2024-10-18T11:00:00.000Z","isDPPNotes":true,"homeworkIds":[{"_id":"67123b0125e163f7a799fe40","actions":["Open","Download","Print"],"topic":"Metals and Non Metals : DHA 04 || Udaan 2.0 2025","note":"DPP","attachmentIds":[{"_id":"67123aff0724ce629c9f82bd","baseUrl":"https:\/\/static.pw.live\/","key":"5eb393ee95fab7468a79d189\/ADMIN\/e0fdd445-e946-4207-949a-80e81af65a88.pdf","name":"Metals and Non Metals _DHA 04.pdf"}],"batchSubjectId":"664c48d84985820018a8c4e9","solutionVideoId":null,"solutionVideoType":"none","solutionVideoUrl":null}],"dRoomId":"664c48940a8ec3f4b8e9ccdf","isBatchDoubtEnabled":true},{"_id":"670927679a072b022843e44a","isFree":false,"status":"PENDING","date":"2024-10-11T00:00:00.000Z","startTime":"2024-10-11T11:00:00.000Z","isDPPNotes":true,"homeworkIds":[{"_id":"6709272d75f6e0d6fd534299","actions":["Open","Download","Print"],"topic":"Metals and Non Metals : DHA 03 || Udaan 2.0 2025","note":"DPP","attachmentIds":[{"_id":"6709272ae17871f16b538b21","baseUrl":"https:\/\/static.pw.live\/","key":"5eb393ee95fab7468a79d189\/ADMIN\/526ec103-280d-4909-bd70-d17e2db37e57.pdf","name":"Metals and Non Metals_DHA 03.pdf"}],"batchSubjectId":"664c48d84985820018a8c4e9","solutionVideoId":null,"solutionVideoType":"none","solutionVideoUrl":null}],"dRoomId":"664c48940a8ec3f4b8e9ccdf","isBatchDoubtEnabled":true},{"_id":"66ffc25670c3eb621e221683","isFree":false,"status":"PENDING","date":"2024-10-04T00:00:00.000Z","startTime":"2024-10-04T11:15:00.000Z","isDPPNotes":true,"homeworkIds":[{"_id":"66ffc210b5916066a1ccc512","actions":["Open","Download","Print"],"topic":"Metals and Non Metals : DHA 02 || Udaan 2.0 2025","note":"DPP","attachmentIds":[{"_id":"66ffc5c7ffea4d8db0d5dad3","baseUrl":"https:\/\/static.pw.live\/","key":"5eb393ee95fab7468a79d189\/ADMIN\/fa2c5fc4-3993-42ed-807c-dce1e5fbae56.pdf","name":"Metals and Non - Metals _DHA 02.pdf"}],"batchSubjectId":"664c48d84985820018a8c4e9","solutionVideoId":null,"solutionVideoType":"none","solutionVideoUrl":null}],"dRoomId":"664c48940a8ec3f4b8e9ccdf","isBatchDoubtEnabled":true},{"_id":"66f6632ba4d3b86de1b902c9","isFree":false,"status":"PENDING","date":"2024-09-27T00:00:00.000Z","startTime":"2024-09-27T11:00:00.000Z","isDPPNotes":true,"homeworkIds":[{"_id":"66f66281a831eda7ace4876c","actions":["Open","Download","Print"],"topic":"Metals and Non Metals  : DHA 01 || Udaan 2.0 2025","note":"DPP","attachmentIds":[{"_id":"66f6627e54a7bf4ce72f59b4","baseUrl":"https:\/\/static.pw.live\/","key":"5eb393ee95fab7468a79d189\/ADMIN\/626598a6-1c71-4cc1-9a48-2ec205411934.pdf","name":"Metals and Non-Metals_DHA 01.pdf"}],"batchSubjectId":"664c48d84985820018a8c4e9","solutionVideoId":null,"solutionVideoType":"none","solutionVideoUrl":null}],"dRoomId":"664c48940a8ec3f4b8e9ccdf","isBatchDoubtEnabled":true}],"DppVideos":[],"exercises":[{"_id":"671714c84f4facd859a79ba8","isFree":false,"status":"COMPLETED","date":"2024-10-22T00:00:00.000Z","startTime":"2024-10-22T09:30:00.000Z","isDPPNotes":false,"exerciseIds":[{"type":"Exercise","availableFor":[],"status":"Active","title":"Metals and Non Metals : DHA 05 MCQ Quiz","content":[{"_id":"671757bbb63c4804df28a3cd","timeline":[],"exerciseId":"671757baf27ee5eff2c6d078","exerciseDetails":{"_id":"671757baf27ee5eff2c6d078","totalQuestions":5,"maxDuration":0,"totalMarks":20}}],"slug":"metals-and-non-metals---dha-05-mcq-quiz-160745"}],"dRoomId":"664c48940a8ec3f4b8e9ccdf","isBatchDoubtEnabled":true},{"_id":"6711bc06dddc2cd517db4363","isFree":false,"status":"PENDING","date":"2024-10-18T00:00:00.000Z","startTime":"2024-10-18T11:00:00.000Z","isDPPNotes":false,"exerciseIds":[{"type":"Exercise","availableFor":[],"status":"Active","title":"Metals and Non Metals : DHA 04 MCQ Quiz","content":[{"_id":"67121f42c37342dd7f88aa00","timeline":[],"exerciseId":"67121f42d0e8dbbf5f9857ce","exerciseDetails":{"_id":"67121f42d0e8dbbf5f9857ce","totalQuestions":5,"maxDuration":0,"totalMarks":20}}],"slug":"metals-and-non-metals---dha-04-mcq-quiz-497446"}],"dRoomId":"664c48940a8ec3f4b8e9ccdf","isBatchDoubtEnabled":true},{"_id":"670802f619347323c1c4d4ae","isFree":false,"status":"PENDING","date":"2024-10-11T00:00:00.000Z","startTime":"2024-10-11T11:00:00.000Z","isDPPNotes":false,"exerciseIds":[{"type":"Exercise","availableFor":[],"status":"Active","title":"Metals and Non - Metals : DHA 03 MCQ Quiz","content":[{"_id":"66bb253a666ad80018f84466","timeline":[],"exerciseId":"66bb253967720dea82c66f38","exerciseDetails":{"_id":"66bb253967720dea82c66f38","totalQuestions":5,"maxDuration":0,"totalMarks":20}}],"slug":"metals-and-non---metals---dha-03-mcq-quiz-498591"}],"dRoomId":"664c48940a8ec3f4b8e9ccdf","isBatchDoubtEnabled":true},{"_id":"66ff685e5b935d0595d5d5ff","isFree":false,"status":"COMPLETED","date":"2024-10-04T00:00:00.000Z","startTime":"2024-10-04T11:15:00.000Z","isDPPNotes":false,"exerciseIds":[{"type":"Exercise","availableFor":[],"status":"Active","title":"Metals and Non - Metals : DHA 02 MCQ Quiz","content":[{"_id":"66b498e42caf4700189fe8db","timeline":[],"exerciseId":"66b498e498b2257dba86d7ed","exerciseDetails":{"_id":"66b498e498b2257dba86d7ed","totalQuestions":5,"maxDuration":0,"totalMarks":20}}],"slug":"metals-and-non---metals---dha-02-mcq-quiz-067737"}],"dRoomId":"664c48940a8ec3f4b8e9ccdf","isBatchDoubtEnabled":true},{"_id":"66f6226e3697a2b7c0b4444a","isFree":false,"status":"COMPLETED","date":"2024-09-27T00:00:00.000Z","startTime":"2024-09-27T11:00:00.000Z","isDPPNotes":false,"exerciseIds":[{"type":"Exercise","availableFor":[],"status":"Active","title":"Metals and Non Metals : DHA 01 MCQ Quiz","content":[{"_id":"66f62efc0fe7f7ccf4c6a641","timeline":[],"exerciseId":"66f62efb4c307b3e62d6ad4e","exerciseDetails":{"_id":"66f62efb4c307b3e62d6ad4e","totalQuestions":5,"maxDuration":0,"totalMarks":20}}],"slug":"metals-and-non-metals---dha-01-mcq-quiz-475696"}],"dRoomId":"664c48940a8ec3f4b8e9ccdf","isBatchDoubtEnabled":true}]}