{"videos":[{"_id":"676d8d6a8f5911019284ff47","isFree":false,"status":"PENDING","date":"2024-12-27T00:00:00.000Z","startTime":"2024-12-27T13:45:00.000Z","isDPPNotes":false,"dRoomId":"67175a700024ca31965ce17b","isBatchDoubtEnabled":true,"isChatEnabled":false,"isCommentDisabled":false,"isDPPVideos":false,"isDoubtEnabled":true,"isPathshala":false,"restrictedSchedule":false,"endTime":"2024-12-27T13:45:00.000Z","restrictedTime":0,"tags":[{"_id":"674db7ebb676332be5032384","name":"Metals and Non Metals"}],"teachers":["66fe831e1754946ed400fa8b"],"timeline":[],"topic":"Metals and Non Metals 03 : Occurrence of Metals ","url":"https:\/\/d1d34p8vz63oiq.cloudfront.net\/ad87f5dc-a4e7-444c-b65f-2b25fc0e70a6\/master.mpd","urlType":"penpencilvdo","ytStreamKey":null,"ytStreamUrl":null,"lectureType":"RECORDED","whiteboardType":"NOTE3","videoDetails":{"_id":"67667f7fa48b1d4319f0cde2","id":"67667f7fa48b1d4319f0cde2","name":"Metals and Non Metals 03 : Occurrence of Metals || 10th Board Booster 2025","image":"https:\/\/static.pw.live\/5eb393ee95fab7468a79d189\/ADMIN\/402d3abc-ee28-4200-aaa7-cc8f6a916927.png","videoUrl":"https:\/\/d1d34p8vz63oiq.cloudfront.net\/ad87f5dc-a4e7-444c-b65f-2b25fc0e70a6\/master.mpd","description":"<!DOCTYPE html>\n<html>\n<head>\n<\/head>\n<body>\n\n<\/body>\n<\/html>","duration":"01:20:40","status":"Ready","types":["DASH","HLS"],"createdAt":"2024-12-21T08:42:39.137Z","drmProtected":false,"findKey":"676d8d6a8f5911019284ff47"},"conversationId":null,"roomId":null,"isLocked":false},{"_id":"6769920b7ffad3514a1340b2","isFree":false,"status":"PENDING","date":"2024-12-24T00:00:00.000Z","startTime":"2024-12-24T13:45:00.000Z","isDPPNotes":false,"dRoomId":"67175a700024ca31965ce17b","isBatchDoubtEnabled":true,"isChatEnabled":false,"isCommentDisabled":false,"isDPPVideos":false,"isDoubtEnabled":true,"isPathshala":false,"restrictedSchedule":false,"endTime":"2024-12-24T13:45:00.000Z","restrictedTime":0,"tags":[{"_id":"674db7ebb676332be5032384","name":"Metals and Non Metals"}],"teachers":["66fe831e1754946ed400fa8b"],"timeline":[],"topic":"Metals and Non Metals 02 :  Chemical Properties of Metal and Non Metals ","url":"https:\/\/d1d34p8vz63oiq.cloudfront.net\/86d7aebb-1c7f-4c62-b837-fdfab5bc40ad\/master.mpd","urlType":"penpencilvdo","ytStreamKey":null,"ytStreamUrl":null,"lectureType":"RECORDED","whiteboardType":"NOTE3","videoDetails":{"_id":"67652740e147c55498006b60","id":"67652740e147c55498006b60","name":"Metals and Non Metals 02 :  Chemical Properties of Metal and Non Metals || 10th Board Booster 2025","image":"https:\/\/static.pw.live\/5eb393ee95fab7468a79d189\/ADMIN\/6c6c533f-d981-4c6e-976f-2fc521c716bf.png","videoUrl":"https:\/\/d1d34p8vz63oiq.cloudfront.net\/86d7aebb-1c7f-4c62-b837-fdfab5bc40ad\/master.mpd","description":"<!DOCTYPE html>\n<html>\n<head>\n<\/head>\n<body>\n\n<\/body>\n<\/html>","duration":"00:58:57","status":"Ready","types":["DASH","HLS"],"createdAt":"2024-12-20T08:13:52.465Z","drmProtected":false,"findKey":"6769920b7ffad3514a1340b2"},"conversationId":null,"roomId":null,"isLocked":false},{"_id":"67645953112bb324593bd3fa","isFree":false,"status":"PENDING","date":"2024-12-20T00:00:00.000Z","startTime":"2024-12-20T13:45:00.000Z","isDPPNotes":false,"dRoomId":"67175a700024ca31965ce17b","isBatchDoubtEnabled":true,"isChatEnabled":false,"isCommentDisabled":false,"isDPPVideos":false,"isDoubtEnabled":true,"isPathshala":false,"restrictedSchedule":false,"endTime":"2024-12-20T13:45:00.000Z","restrictedTime":0,"tags":[{"_id":"674db7ebb676332be5032384","name":"Metals and Non Metals"}],"teachers":["66fe831e1754946ed400fa8b"],"timeline":[],"topic":"Metals and Non Metals 01 : Introduction to Metals and Non-Metals || Chemical Properties of Metal and Non Metals","url":"https:\/\/d1d34p8vz63oiq.cloudfront.net\/ce7944aa-b67e-4790-ae32-95cbb7be082c\/master.mpd","urlType":"penpencilvdo","ytStreamKey":null,"ytStreamUrl":null,"lectureType":"RECORDED","whiteboardType":"NOTE3","videoDetails":{"_id":"6763e77b9d3387f8f0ec4b09","id":"6763e77b9d3387f8f0ec4b09","name":"Metals and Non Metals 01 : Introduction to Metals and Non-Metals || Chemical Properties of Metal and Non Metals || 10th Board Booster 2025","image":"https:\/\/static.pw.live\/5eb393ee95fab7468a79d189\/ADMIN\/ecb74089-ef46-4755-97b4-5232e245c9e5.png","videoUrl":"https:\/\/d1d34p8vz63oiq.cloudfront.net\/ce7944aa-b67e-4790-ae32-95cbb7be082c\/master.mpd","description":"<!DOCTYPE html>\n<html>\n<head>\n<\/head>\n<body>\n\n<\/body>\n<\/html>","duration":"01:33:31","status":"Ready","types":["DASH","HLS"],"createdAt":"2024-12-19T09:29:31.957Z","drmProtected":false,"findKey":"67645953112bb324593bd3fa"},"conversationId":null,"roomId":null,"isLocked":false}],"notes":[{"_id":"676d8d6a8f5911019284ff47","isFree":false,"status":"PENDING","date":"2024-12-27T00:00:00.000Z","startTime":"2024-12-27T13:45:00.000Z","isDPPNotes":false,"homeworkIds":[{"_id":"676e581af7e6d94871906eed","actions":["Open","Download","Print"],"topic":"Metals and Non Metals 03 : Class Notes || 10th Board Booster 2025","note":"Class Notes","attachmentIds":[{"_id":"676e5818c569d7ea00af194a","baseUrl":"https:\/\/static.pw.live\/","key":"5eb393ee95fab7468a79d189\/ADMIN\/effd3c3d-2aa5-4c6a-bf4c-dd2e523f61e5.pdf","name":"Metals and Non Metals 03  Class Notes.pdf"}],"batchSubjectId":"67175aef3f216aca0bd9334e","solutionVideoId":null,"solutionVideoType":"none","solutionVideoUrl":null}],"dRoomId":"67175a700024ca31965ce17b","isBatchDoubtEnabled":true},{"_id":"6769920b7ffad3514a1340b2","isFree":false,"status":"PENDING","date":"2024-12-24T00:00:00.000Z","startTime":"2024-12-24T13:45:00.000Z","isDPPNotes":false,"homeworkIds":[{"_id":"6769994d6b2cc5d7415b195e","actions":["Open","Download","Print"],"topic":"Metals and Non Metals 02 : Class Notes || 10th Board Booster 2025","note":"Class Notes","attachmentIds":[{"_id":"6769994b15586aabf2ece1f1","baseUrl":"https:\/\/static.pw.live\/","key":"5eb393ee95fab7468a79d189\/ADMIN\/7840d82e-17dd-4833-8f4d-33c300b01c07.pdf","name":"Metals and Non Metals 02  Class Notes.pdf"}],"batchSubjectId":"67175aef3f216aca0bd9334e","solutionVideoId":null,"solutionVideoType":"none","solutionVideoUrl":null}],"dRoomId":"67175a700024ca31965ce17b","isBatchDoubtEnabled":true},{"_id":"67645953112bb324593bd3fa","isFree":false,"status":"PENDING","date":"2024-12-20T00:00:00.000Z","startTime":"2024-12-20T13:45:00.000Z","isDPPNotes":false,"homeworkIds":[{"_id":"6765378547ba8a9f7b448d4e","actions":["Open","Download","Print"],"topic":"Metals and Non Metals 01 : Class Notes || 10th Board Booster 2025","note":"Class Notes","attachmentIds":[{"_id":"67653783214f7dd9aa32a5a1","baseUrl":"https:\/\/static.pw.live\/","key":"5eb393ee95fab7468a79d189\/ADMIN\/a92cebd9-e43f-42b2-88ad-5153ee3d998b.pdf","name":"Metals and Non Metals 01 Class Notes.pdf"}],"batchSubjectId":"67175aef3f216aca0bd9334e","solutionVideoId":null,"solutionVideoType":"none","solutionVideoUrl":null}],"dRoomId":"67175a700024ca31965ce17b","isBatchDoubtEnabled":true}],"DppNotes":[{"_id":"676ea106b1a78c6656696537","isFree":false,"status":"PENDING","date":"2024-12-27T00:00:00.000Z","startTime":"2024-12-27T13:45:00.000Z","isDPPNotes":true,"homeworkIds":[{"_id":"676ea0f3acd77bf0446eaaac","actions":["Open","Download","Print"],"topic":"Metals and Non Metals : DHA 03 || 10th Board Booster 2025","note":"DPP","attachmentIds":[{"_id":"676ea0f1c569d7ea00af2dde","baseUrl":"https:\/\/static.pw.live\/","key":"5eb393ee95fab7468a79d189\/ADMIN\/5bde38b5-951c-46f0-b7d6-0dbcf6416ac3.pdf","name":"Metals and Non Metals  DHA 03 .pdf"}],"batchSubjectId":"67175aef3f216aca0bd9334e","solutionVideoId":null,"solutionVideoType":"none","solutionVideoUrl":null}],"dRoomId":"67175a700024ca31965ce17b","isBatchDoubtEnabled":true},{"_id":"676aaa7704a38176fbb70955","isFree":false,"status":"PENDING","date":"2024-12-24T00:00:00.000Z","startTime":"2024-12-24T13:45:00.000Z","isDPPNotes":true,"homeworkIds":[{"_id":"676aa6ad47dde9683716e349","actions":["Open","Download","Print"],"topic":"Metals and Non Metals : DHA 02 || 10th Board Booster 2025","note":"DPP","attachmentIds":[{"_id":"676aa6ab9b4b195828be2d3c","baseUrl":"https:\/\/static.pw.live\/","key":"5eb393ee95fab7468a79d189\/ADMIN\/0e16c412-813c-48e8-94f1-4804fc3f9e87.pdf","name":"Metals and Non Metals  DHA 02 .pdf"}],"batchSubjectId":"67175aef3f216aca0bd9334e","solutionVideoId":null,"solutionVideoType":"none","solutionVideoUrl":null}],"dRoomId":"67175a700024ca31965ce17b","isBatchDoubtEnabled":true},{"_id":"676546b32d56922b771607fe","isFree":false,"status":"PENDING","date":"2024-12-20T00:00:00.000Z","startTime":"2024-12-20T13:45:00.000Z","isDPPNotes":true,"homeworkIds":[{"_id":"676544db7e70512e4afd68f1","actions":["Open","Download","Print"],"topic":"Metals and Non Metals : DHA 01 || 10th Board Booster 2025","note":"DPP","attachmentIds":[{"_id":"676544ef214f7dd9aa32a95f","baseUrl":"https:\/\/static.pw.live\/","key":"5eb393ee95fab7468a79d189\/ADMIN\/7b99d029-de6e-4368-90d6-401149db8405.pdf","name":"Metals and Non Metals DHA 01.pdf"}],"batchSubjectId":"67175aef3f216aca0bd9334e","solutionVideoId":null,"solutionVideoType":"none","solutionVideoUrl":null}],"dRoomId":"67175a700024ca31965ce17b","isBatchDoubtEnabled":true}],"DppVideos":[],"exercises":[{"_id":"676d8d6a8f5911019284ff47","isFree":false,"status":"PENDING","date":"2024-12-27T00:00:00.000Z","startTime":"2024-12-27T13:45:00.000Z","isDPPNotes":false,"exerciseIds":[{"type":"Exercise","availableFor":[],"status":"Active","title":"Metals and Non Metals : DHA 03 MCQ Quiz","content":[{"_id":"676ea1e4accfc8e014659071","timeline":[],"exerciseId":"676ea1e4fdbc1c2eac481139","exerciseDetails":{"_id":"676ea1e4fdbc1c2eac481139","totalQuestions":10,"maxDuration":0,"totalMarks":40}}],"slug":"metals-and-non-metals---dha-03-mcq-quiz-998656"}],"dRoomId":"67175a700024ca31965ce17b","isBatchDoubtEnabled":true},{"_id":"6769920b7ffad3514a1340b2","isFree":false,"status":"PENDING","date":"2024-12-24T00:00:00.000Z","startTime":"2024-12-24T13:45:00.000Z","isDPPNotes":false,"exerciseIds":[{"type":"Exercise","availableFor":[],"status":"Active","title":"Metals and Non Metals : DHA 02 MCQ Quiz","content":[{"_id":"676aaa2b4b9b99612b71281b","timeline":[],"exerciseId":"676aaa2be89db11c8475a98a","exerciseDetails":{"_id":"676aaa2be89db11c8475a98a","totalQuestions":10,"maxDuration":0,"totalMarks":40}}],"slug":"metals-and-non-metals---dha-02-mcq-quiz-871428"}],"dRoomId":"67175a700024ca31965ce17b","isBatchDoubtEnabled":true},{"_id":"67645953112bb324593bd3fa","isFree":false,"status":"PENDING","date":"2024-12-20T00:00:00.000Z","startTime":"2024-12-20T13:45:00.000Z","isDPPNotes":false,"exerciseIds":[{"type":"Exercise","availableFor":[],"status":"Active","title":"Metals and Non Metals : DHA 01 MCQ Quiz","content":[{"_id":"67654675672a3bf846ffca0a","timeline":[],"exerciseId":"6765467580f7f2622a18ff2f","exerciseDetails":{"_id":"6765467580f7f2622a18ff2f","totalQuestions":10,"maxDuration":0,"totalMarks":40}}],"slug":"metals-and-non-metals---dha-01-mcq-quiz-214119"}],"dRoomId":"67175a700024ca31965ce17b","isBatchDoubtEnabled":true}]}