{"videos":[{"_id":"67506378e956742efa1637ac","isFree":false,"status":"PENDING","date":"2024-12-05T00:00:00.000Z","startTime":"2024-12-05T09:45:00.000Z","isDPPNotes":false,"dRoomId":"67175a700024ca31965ce17b","isBatchDoubtEnabled":true,"isChatEnabled":false,"isCommentDisabled":false,"isDPPVideos":false,"isDoubtEnabled":true,"isPathshala":false,"restrictedSchedule":false,"endTime":"2024-12-05T09:45:00.000Z","restrictedTime":0,"tags":[{"_id":"67506320e2d359be7a580f56","name":"Federalism - (Political Science)"}],"teachers":["628f242e030f8500127b5566"],"timeline":[],"topic":"Political Science - Federalism : One Shot ","url":"https:\/\/d1d34p8vz63oiq.cloudfront.net\/4442314c-cba7-4026-8c7a-c7ad55b56a37\/master.mpd","urlType":"penpencilvdo","ytStreamKey":null,"ytStreamUrl":null,"lectureType":"RECORDED","whiteboardType":"NOTE3","videoDetails":{"_id":"675097fcd8d45908e9b990ef","id":"675097fcd8d45908e9b990ef","name":"Political Science - Federalism : One Shot || 10th Board Booster 2025","image":"https:\/\/static.pw.live\/5eb393ee95fab7468a79d189\/ADMIN\/31c907a6-0c39-4af4-bd2f-1286af304866.png","videoUrl":"https:\/\/d1d34p8vz63oiq.cloudfront.net\/4442314c-cba7-4026-8c7a-c7ad55b56a37\/master.mpd","description":"<!DOCTYPE html>\n<html>\n<head>\n<\/head>\n<body>\n\n<\/body>\n<\/html>","duration":"01:18:17","status":"Ready","types":["DASH","HLS"],"createdAt":"2024-12-04T17:57:16.536Z","drmProtected":false,"findKey":"67506378e956742efa1637ac"},"conversationId":null,"roomId":null,"isLocked":false}],"notes":[{"_id":"67506378e956742efa1637ac","isFree":false,"status":"PENDING","date":"2024-12-05T00:00:00.000Z","startTime":"2024-12-05T09:45:00.000Z","isDPPNotes":false,"homeworkIds":[{"_id":"675149c459a86d17a29883d1","actions":["Open","Download","Print"],"topic":"Political Science - Federalism : Class Notes || 10th Board Booster 2025","note":"Class Notes","attachmentIds":[{"_id":"675149c1ee9565b4552c5027","baseUrl":"https:\/\/static.pw.live\/","key":"5eb393ee95fab7468a79d189\/ADMIN\/e07831dc-feff-49b6-94e1-d7b84e0fe10d.pdf","name":"Political Science - Federalism  Class Notes.pdf"}],"batchSubjectId":"67175afa90f87af83b9dba96","solutionVideoId":null,"solutionVideoType":"none","solutionVideoUrl":null}],"dRoomId":"67175a700024ca31965ce17b","isBatchDoubtEnabled":true}],"DppNotes":[{"_id":"6751526c653d2003fac0cfcc","isFree":false,"status":"PENDING","date":"2024-12-05T00:00:00.000Z","startTime":"2024-12-05T09:45:00.000Z","isDPPNotes":true,"homeworkIds":[{"_id":"675149e2fd1fbca78fd037dc","actions":["Open","Download","Print"],"topic":"Political Science - Federalism : DHA 01 || 10th Board Booster 2025","note":"DPP","attachmentIds":[{"_id":"675149e0ad0f6275a3c2cffa","baseUrl":"https:\/\/static.pw.live\/","key":"5eb393ee95fab7468a79d189\/ADMIN\/3423e3c2-9771-4ff3-ba42-432e3695c924.pdf","name":"Political Science - Federalism  DHA 01.pdf"}],"batchSubjectId":"67175afa90f87af83b9dba96","solutionVideoId":null,"solutionVideoType":"none","solutionVideoUrl":null}],"dRoomId":"67175a700024ca31965ce17b","isBatchDoubtEnabled":true}],"DppVideos":[],"exercises":[{"_id":"67506378e956742efa1637ac","isFree":false,"status":"PENDING","date":"2024-12-05T00:00:00.000Z","startTime":"2024-12-05T09:45:00.000Z","isDPPNotes":false,"exerciseIds":[{"type":"Exercise","availableFor":[],"status":"Active","title":"Political Science - Federalism : DHA 01 MCQ Quiz","content":[{"_id":"67515486a9062c28c96ff42b","timeline":[],"exerciseId":"67515486cfb9de0e127ad91a","exerciseDetails":{"_id":"67515486cfb9de0e127ad91a","totalQuestions":18,"maxDuration":0,"totalMarks":72}}],"slug":"political-science---federalism---dha-01-mcq-quiz-439846"}],"dRoomId":"67175a700024ca31965ce17b","isBatchDoubtEnabled":true}]}